CLASSIFIERS.txt
LICENSE.txt
MANIFEST.in
README.rst
requirements.pip
setup.py
src/django_historicalrecords.egg-info/PKG-INFO
src/django_historicalrecords.egg-info/SOURCES.txt
src/django_historicalrecords.egg-info/dependency_links.txt
src/django_historicalrecords.egg-info/requires.txt
src/django_historicalrecords.egg-info/top_level.txt
src/history/__init__.py
src/history/manager.py
src/history/models.py